<?xml version="1.0" encoding="UTF-8"?>
<EndpointDescription xmlns="http://clarin.eu/fcs/endpoint-description"
                     xmlns:xsi="http://www.w3.org/2001/XMLSchema-instance"
                     xsi:schemaLocation="http://clarin.eu/fcs/endpoint-description ../../schema/Core_2/Endpoint-Description.xsd"
                     version="2">
    <Capabilities>
        <Capability>http://clarin.eu/fcs/capability/basic-search</Capability>
    </Capabilities>
    <SupportedDataViews>
        <SupportedDataView id="hits" delivery-policy="send-by-default">application/x-clarin-fcs-hits+xml</SupportedDataView>
    </SupportedDataViews>
    <SupportedLayers>
        <SupportedLayer id="word" result-id="http://existdb.ilc4clarin.ilc.cnr.it/exist/ilc4clarin/fcs/layer/word">text</SupportedLayer>
    </SupportedLayers>
  
    <Resources>
        <Resources>
            <Resource pid="/db/ilc4clarin/data/panacea">
                <Title xml:lang="it">Corpus Panacea eXist-db demo</Title>
                <Title xml:lang="en">Corpus Panacea eXist-db demo</Title>
                <Description xml:lang="it">Corpus Panacea eXist-db demo</Description>
                <Description xml:lang="en">Corpus Panacea eXist-db demo</Description>
                <LandingPageURI>http://existdb.ilc4clarin.ilc.cnr.it/exist/rest/db/ilc4clarin/data/panacea</LandingPageURI>
                <Languages>
                    <Language>ita</Language>
                </Languages>
                <AvailableDataViews ref="hits"/>
                <AvailableLayers ref="word"/>                   
            </Resource>
            <Resource pid="/db/ilc4clarin/data/test">
                <Title xml:lang="it">Corpus Test eXist-db demo</Title>
                <Title xml:lang="en">Corpus Test eXist-db demo</Title>
                <Description xml:lang="it">Corpus Panacea eXist-db demo</Description>
                <Description xml:lang="en">Corpus Panacea eXist-db demo</Description>
                <LandingPageURI>http://existdb.ilc4clarin.ilc.cnr.it/exist/rest/db/ilc4clarin/data/test</LandingPageURI>
                <Languages>
                    <Language>ita</Language>
                </Languages>
                <AvailableDataViews ref="hits"/>
                <AvailableLayers ref="word"/>
            </Resource>
        </Resources>
    </Resources>
</EndpointDescription>
